physense_sim/__init__.py
physense_sim/bLedOff.png
physense_sim/bLedOn.png
physense_sim/buzzer.wav
physense_sim/gLedOff.png
physense_sim/gLedOn.png
physense_sim/moon.png
physense_sim/rLedOff.png
physense_sim/rLedOn.png
physense_sim/speaker.png
physense_sim/sun.png
physense_sim/yLedOff.png
physense_sim/yLedOn.png
physense_sim-2.0.0.dist-info/LICENSE.txt
physense_sim-2.0.0.dist-info/METADATA
physense_sim-2.0.0.dist-info/WHEEL
physense_sim-2.0.0.dist-info/entry_points.txt
physense_sim-2.0.0.dist-info/top_level.txt
physense_sim-2.0.0.dist-info/RECORD
