Metadata-Version: 2.1
Name: physense-sim
Version: 2.0.0
Summary: A simulator for itn160
Home-page: https://github.com/primeteacher/physense_sim
Author: Jason Silverstein
Author-email: jsilver5@dtcc.edu
License: UNKNOWN
Keywords: itn160
Platform: UNKNOWN
Classifier: Development Status :: 3 - Alpha
Classifier: Topic :: Software Development :: Build Tools
Classifier: License :: OSI Approved :: MIT License
Classifier: Programming Language :: Python :: 3
Requires-Dist: guizero
Requires-Dist: pygame
